{
    "2020-11-03": {
        "04:00:00": null,
        "09:00:00": null,
        "10:00:00": null,
        "08:00:00": null,
        "11:00:00": {
            "hours": {
                "10:00:00": {
                    "1": {
                        "tid": [
                            "1323482140533690368",
                            "1323482378304692226"
                        ],
                        "tid_count": 2
                    },
                    "11": {
                        "tid": [
                            "1323482504657989633"
                        ],
                        "tid_count": 1
                    },
                    "12": {
                        "tid": [
                            "1323482366073921537",
                            "1323482517173727232"
                        ],
                        "tid_count": 2
                    },
                    "13": {
                        "tid": [
                            "1323482486895079424",
                            "1323482034153558018",
                            "1323482319391395840"
                        ],
                        "tid_count": 3
                    }
                },
                "11:00:00": {
                    "2": {
                        "tid": [
                            "1323483079080435712",
                            "1323483050307592192"
                        ],
                        "tid_count": 2
                    },
                    "11": {
                        "tid": [
                            "1323482744295337984",
                            "1323482713987272704",
                            "1323482855708762113"
                        ],
                        "tid_count": 3
                    },
                    "12": {
                        "tid": [
                            "1323482843767451649",
                            "1323483394102095873",
                            "1323483325088976897",
                            "1323483256356962304",
                            "1323483176002465792",
                            "1323482902529650688"
                        ],
                        "tid_count": 6
                    },
                    "13": {
                        "tid": [
                            "1323483070977040384",
                            "1323482815795666945",
                            "1323482862251728896",
                            "1323482685403099137",
                            "1323482924402974721",
                            "1323482802130624513",
                            "1323482597515616262",
                            "1323483075674664961"
                        ],
                        "tid_count": 8
                    },
                    "102": {
                        "tid": [
                            "1323483284936904706"
                        ],
                        "tid_count": 1
                    }
                }
            },
            "category": {
                "1": {
                    "tid": [
                        "1323482140533690368",
                        "1323482378304692226"
                    ]
                },
                "2": {
                    "tid": [
                        "1323483079080435712",
                        "1323483050307592192"
                    ]
                },
                "102": {
                    "tid": [
                        "1323483284936904706"
                    ]
                },
                "11": {
                    "tid": [
                        "1323482744295337984",
                        "1323482713987272704",
                        "1323482504657989633",
                        "1323482855708762113"
                    ]
                },
                "12": {
                    "tid": [
                        "1323482843767451649",
                        "1323483394102095873",
                        "1323483325088976897",
                        "1323483256356962304",
                        "1323483176002465792",
                        "1323482902529650688",
                        "1323482366073921537",
                        "1323482517173727232"
                    ]
                },
                "13": {
                    "tid": [
                        "1323483070977040384",
                        "1323482815795666945",
                        "1323482486895079424",
                        "1323482862251728896",
                        "1323482685403099137",
                        "1323482924402974721",
                        "1323482802130624513",
                        "1323482034153558018",
                        "1323482597515616262",
                        "1323483075674664961",
                        "1323482319391395840"
                    ]
                }
            },
            "second": {
                "09:59:20": {
                    "12": {
                        "tid": [
                            "1323482366073921537"
                        ]
                    }
                },
                "10:01:20": {
                    "11": {
                        "tid": [
                            "1323482855708762113"
                        ]
                    },
                    "12": {
                        "tid": [
                            "1323482843767451649"
                        ]
                    },
                    "13": {
                        "tid": [
                            "1323482862251728896"
                        ]
                    }
                },
                "09:59:50": {
                    "13": {
                        "tid": [
                            "1323482486895079424"
                        ]
                    }
                },
                "10:01:30": {
                    "12": {
                        "tid": [
                            "1323482902529650688"
                        ]
                    }
                },
                "10:02:40": {
                    "12": {
                        "tid": [
                            "1323483176002465792"
                        ]
                    }
                },
                "10:03:30": {
                    "12": {
                        "tid": [
                            "1323483394102095873"
                        ]
                    }
                },
                "09:59:10": {
                    "13": {
                        "tid": [
                            "1323482319391395840"
                        ]
                    }
                },
                "10:01:00": {
                    "11": {
                        "tid": [
                            "1323482744295337984"
                        ]
                    }
                },
                "10:02:10": {
                    "2": {
                        "tid": [
                            "1323483079080435712",
                            "1323483050307592192"
                        ]
                    },
                    "13": {
                        "tid": [
                            "1323483070977040384",
                            "1323483075674664961"
                        ]
                    }
                },
                "10:01:10": {
                    "13": {
                        "tid": [
                            "1323482815795666945",
                            "1323482802130624513"
                        ]
                    }
                },
                "10:01:40": {
                    "13": {
                        "tid": [
                            "1323482924402974721"
                        ]
                    }
                },
                "10:00:20": {
                    "13": {
                        "tid": [
                            "1323482597515616262"
                        ]
                    }
                },
                "09:58:10": {
                    "13": {
                        "tid": [
                            "1323482034153558018"
                        ]
                    }
                },
                "10:00:50": {
                    "11": {
                        "tid": [
                            "1323482713987272704"
                        ]
                    }
                },
                "09:59:30": {
                    "1": {
                        "tid": [
                            "1323482378304692226"
                        ]
                    }
                },
                "10:00:40": {
                    "13": {
                        "tid": [
                            "1323482685403099137"
                        ]
                    }
                },
                "10:03:00": {
                    "12": {
                        "tid": [
                            "1323483256356962304"
                        ]
                    },
                    "102": {
                        "tid": [
                            "1323483284936904706"
                        ]
                    }
                },
                "10:00:00": {
                    "11": {
                        "tid": [
                            "1323482504657989633"
                        ]
                    },
                    "12": {
                        "tid": [
                            "1323482517173727232"
                        ]
                    }
                },
                "10:03:10": {
                    "12": {
                        "tid": [
                            "1323483325088976897"
                        ]
                    }
                },
                "09:58:30": {
                    "1": {
                        "tid": [
                            "1323482140533690368"
                        ]
                    }
                }
            },
            "user": {
                "$1272141667819089920": 1,
                "$1167616299754614786": 1,
                "$985298882589372416": 1,
                "$1184349707230838785": 1,
                "$1214480994062848000": 1,
                "$1131429685638778880": 1,
                "$1286106767903121415": 1,
                "$1299681543841959938": 1,
                "$1292651210630000641": 1,
                "$1287021538512838657": 1,
                "$1304013519310843908": 1,
                "$1165993590851457027": 2,
                "$1183648422642868230": 1,
                "$1287230604568694785": 1,
                "$1153568212056862720": 1,
                "$1323251617009815553": 1,
                "$1257765735553617921": 1,
                "$1294873884563390471": 1,
                "$1139494478606024704": 1,
                "$1107085753337565184": 1,
                "$1180300483497353216": 1,
                "$1303389200352448515": 1,
                "$1183687559852879873": 1,
                "$1155356110343139328": 1,
                "$1243940675105591296": 1,
                "$1041856872184246272": 1,
                "$941328161035264000": 1
            },
            "mentions": {
                "@DRNne_EM7": 1,
                "@CHIMMYxJEON": 1,
                "@twerkitjimin": 1,
                "@btaens_": 2,
                "@KOOKIESNMILKIES": 1,
                "@winterkimchitae": 1,
                "@euphoriluvs": 3,
                "@AlinSaji1": 2,
                "@jeon_cole": 1,
                "@bts_bighit": 1,
                "@joonfier": 1,
                "@kkooky_": 1,
                "@taetaengena": 2,
                "@skzhyunlixx": 1,
                "@RSPCTJOON": 1,
                "@tkfIirt": 1,
                "@gijiminiebts": 1,
                "@mamshmoon": 1,
                "@BTS_twt": 9,
                "@NOCAPS_": 1,
                "@kthslips": 1,
                "@SeriousOT7": 1
            },
            "hashtags": {
                "#Taetae": 1,
                "#ARMY": 2,
                "#ARSD": 25,
                "#BTS": 2,
                "#Taehyung": 2,
                "#ARSDSelcaDay": 1,
                "#ARMYSelcaDay": 2,
                "#JUNGKOOK": 1,
                "#TAEHUYNG": 1,
                "#ARMYSeIcaDay": 28,
                "#BTSARMY": 2
            }
        },
        "01:00:00": null,
        "07:00:00": null,
        "02:00:00": null,
        "06:00:00": null,
        "03:00:00": null,
        "05:00:00": null
    },
    "2020-11-02": null,
    "2020-10-31": null,
    "2020-11-01": null
}